HList.py
HTK_MLF_io.py
HTK_model_parse.py.new
MANIFEST.in
MFCCFile.py
MakeDoc
Num.py
Numeric_gpk.py
__init__.py
accent_spec.py
arclist.pm
arith.pm
array_window.py
avio.py
bark_scale.py
beamsearch.py
blue_data_attributes.py
blue_data_selector.py
chunkio.py
convex_hull2d.py
cosmology.new.pm
dict_vector.py
dictops.py
die.py
die2.py
do_exec.pm
do_exec.py
do_pgplot.py
ds9_region.py
dyn_prog.py
edit_distance.py
entropy.py
epydoc.config
erb_scale.py
escape.pm
evolution.py
fake_file.py
fiat_merge.py
fiatio.py
find_home.py
find_ngram.py
findleak.py
findpath.pm
ftest.py
fuzzygraph.py
g2_select.py
g_closure.py
g_datetime.py
g_ds9.py
g_encode.py
g_entropy.py
g_exec.py
g_implements.py
g_keyed_accum.py
g_lin_fit.py
g_localfit.py
g_lpc.py
g_pipe.py
g_pipe_old.py
g_place_label.py
g_pylab.py
g_selector.py
gpk_getopt.py
gpk_hdr.py
gpk_lapack.py
gpk_lsq.py
gpk_rlsq.py
gpk_writer.py
gpkequations.py
gpkmisc.py
hilbert_xform.py
imop.pm
integrate_exp.pm
ipydoc.py
kl_dist.py
lapack_dgesv.py
lapack_dsyevd.py
load_mod.py
lreg_fill.py
m22.pm
makemake.py
matrix_arrange.py
matrix_arrange_entropy.py
matrix_rearrange_labels.py
mcmc.py
mcmcS2.py
mcmcSQ.py
mcmc_big.py
mcmc_helper.py
mcmc_idxr.py
mcmc_logger.py
mcmc_m4p.py
mcmc_mpi.py
mcmc_pypar.py
md_scaling.py
multivariance_classes.py
multivariance_mm.py
multivariance_q.py
multivariate_normal.py
named_block_file.py
nbest.py
nice_hash.py
nice_hash.py.old
nicknames.py
nmf.py
opt.py
ortho_poly.py
parse_tree_number.py
parsedata.pm
permute.py
pylab_oneaxis.py
pylab_starplot.py
q3html.py
ran.native_perl.pm
read_dicom.py
resample.py
rfc822.pm
robust_multivariate.py
root.py
rubber_array.py
s_lin_fit.py
sbd_array.py
segmentfile.py
setup.py
sharp_energy.py
solve_sum_abs.py
spread_jobs.py
stats.py
synch_demod.py
tsops.py
wavesurfer_lab.py
wavio.py
weighted_percentile.py
wnpp.pm
wnpp2.pm
wnpp_combine.pm
wnpp_local.pm
wnpp_real.pm
wnpp_rules.pm
wnpp_wn.pm
xwaves_errs.py
xwaves_lab.py
xwaves_mark.py
./HList.py
./HTK_MLF_io.py
./MFCCFile.py
./Num.py
gmisclib.egg-info/PKG-INFO
gmisclib.egg-info/SOURCES.txt
gmisclib.egg-info/dependency_links.txt
gmisclib.egg-info/requires.txt
gmisclib.egg-info/top_level.txt