Metadata-Version: 1.0
Name: gmisclib
Version: 0.64.9
Summary: Various Python Libraries, mostly scientific purposes
Home-page: http://kochanski.org/gpk/code/speechresearch/gmisclib
Author: Greg Kochanski
Author-email: gpk@kochanski.org
License: GPL2
Keywords: phonetics speech computational linguistics basic library python science optimize
Platform: All
Classifier: License :: OSI Approved :: GNU General Public License (GPL)
Classifier: Operating System :: OS Independent
Classifier: Development Status :: 3 - Alpha
Classifier: Topic :: Scientific/Engineering
Classifier: Intended Audience :: Science/Research
Classifier: Programming Language :: Python
Classifier: Operating System :: OS Independent
Classifier: Programming Language :: Python
